{
	"pages": [ //pages数组中第一项表示应用启动页，参考：https://uniapp.dcloud.io/collocation/pages
		{
			"path": "pages/index/index",
			"style": {
				"navigationStyle":"custom"
			}
		}, 
		{
			"path": "pages/classify/classify",
			"style": {
			}

		}, 
		{
			"path": "pages/user/user",
			"style": {
				"navigationBarTitleText": "用户中心"
			}

		}
	],
	"globalStyle": {
		"navigationBarTextStyle": "black",
		"navigationBarTitleText": "小小课堂",
		"navigationBarBackgroundColor": "#F8F8F8",
		"backgroundColor": "#F8F8F8"
	},
	"tabBar": {
		"color": "#333333",
		"selectedColor": "#30d4e9",
		"backgroundColor": "#FFFFFF",
		"list": [{
				"pagePath": "pages/index/index",
				"text": "首页",
				"iconPath": "static/home.png",
				"selectedIconPath": "static/home-select.png"
			},
			{
				"pagePath": "pages/classify/classify",
				"text": "课程中心",
				"iconPath": "static/list.png",
				"selectedIconPath": "static/list-select.png"
			},
			{
				"pagePath": "pages/user/user",
				"text": "用户中心",
				"iconPath": "static/user.png",
				"selectedIconPath": "static/user-select.png"
			}
		]
	}
}
